MANIFEST.in
README.txt
setup.cfg
setup.py
docs/HISTORY.txt
docs/INSTALL.txt
docs/LICENSE.GPL
docs/LICENSE.txt
src/collective/__init__.py
src/collective.videolink.egg-info/PKG-INFO
src/collective.videolink.egg-info/SOURCES.txt
src/collective.videolink.egg-info/dependency_links.txt
src/collective.videolink.egg-info/entry_points.txt
src/collective.videolink.egg-info/namespace_packages.txt
src/collective.videolink.egg-info/not-zip-safe
src/collective.videolink.egg-info/requires.txt
src/collective.videolink.egg-info/top_level.txt
src/collective/videolink/__init__.py
src/collective/videolink/configure.zcml
src/collective/videolink/indexers.py
src/collective/videolink/interfaces.py
src/collective/videolink/profiles.zcml
src/collective/videolink/setuphandlers.py
src/collective/videolink/testing.py
src/collective/videolink/upgrades.py
src/collective/videolink/upgrades.zcml
src/collective/videolink/utility.py
src/collective/videolink/browser/__init__.py
src/collective/videolink/browser/configure.zcml
src/collective/videolink/browser/embeddedvideo.pt
src/collective/videolink/browser/embeddedvideos.pt
src/collective/videolink/browser/view.py
src/collective/videolink/profiles/default/catalog.xml
src/collective/videolink/profiles/default/collective.videolink_marker.txt
src/collective/videolink/profiles/default/metadata.xml
src/collective/videolink/profiles/default/types.xml
src/collective/videolink/profiles/default/types/Collection.xml
src/collective/videolink/profiles/default/types/Folder.xml
src/collective/videolink/profiles/default/types/Topic.xml
src/collective/videolink/tests/__init__.py
src/collective/videolink/tests/test_content.py