Metadata-Version: 1.1
Name: collective.videolink
Version: 5.0a5
Summary: Display link content type as embedded video, provide a video gallery view
Home-page: http://github.com/collective/collective.videolink
Author: David Bain
Author-email: david.bain@alteroo.com
License: GPL
Platform: UNKNOWN
Classifier: Framework :: Plone
Classifier: Framework :: Plone :: 5.0
Classifier: Framework :: Plone :: 5.1
Classifier: Programming Language :: Zope
Classifier: Programming Language :: Python
Classifier: Topic :: Software Development :: Libraries :: Python Modules
Classifier: Programming Language :: Python :: 2.7
Classifier: License :: OSI Approved :: GNU General Public License (GPL)
